{
"meta":{"test_sets":[],"test_metrics":[],"learn_metrics":[{"best_value":"Min","name":"RMSE"}],"launch_mode":"Train","parameters":"","iteration_count":30,"learn_sets":["learn"],"name":"experiment"},
"iterations":[
{"learn":[57644.42193],"iteration":0,"passed_time":0.001805492732,"remaining_time":0.05235928924},
{"learn":[55139.39712],"iteration":1,"passed_time":0.003238140612,"remaining_time":0.04533396857},
{"learn":[52353.49975],"iteration":2,"passed_time":0.01490706135,"remaining_time":0.1341635521},
{"learn":[51299.60294],"iteration":3,"passed_time":0.03149422096,"remaining_time":0.2047124363},
{"learn":[50073.07343],"iteration":4,"passed_time":0.03262043805,"remaining_time":0.1631021903},
{"learn":[49573.90131],"iteration":5,"passed_time":0.03366959976,"remaining_time":0.134678399},
{"learn":[48927.14505],"iteration":6,"passed_time":0.03474338044,"remaining_time":0.1141568215},
{"learn":[48227.82201],"iteration":7,"passed_time":0.04742451284,"remaining_time":0.1304174103},
{"learn":[47783.5555],"iteration":8,"passed_time":0.04900675644,"remaining_time":0.1143490984},
{"learn":[47045.56658],"iteration":9,"passed_time":0.05011507736,"remaining_time":0.1002301547},
{"learn":[46668.68482],"iteration":10,"passed_time":0.0618487545,"remaining_time":0.1068296669},
{"learn":[46453.1671],"iteration":11,"passed_time":0.06304948482,"remaining_time":0.09457422723},
{"learn":[46037.85179],"iteration":12,"passed_time":0.06409587982,"remaining_time":0.083817689},
{"learn":[45649.55613],"iteration":13,"passed_time":0.06517831529,"remaining_time":0.07448950319},
{"learn":[45578.96383],"iteration":14,"passed_time":0.06626530785,"remaining_time":0.06626530785},
{"learn":[45337.35279],"iteration":15,"passed_time":0.0805548049,"remaining_time":0.07048545429},
{"learn":[44790.08586],"iteration":16,"passed_time":0.08193478815,"remaining_time":0.06265601447},
{"learn":[44622.39177],"iteration":17,"passed_time":0.09340893493,"remaining_time":0.06227262329},
{"learn":[44269.6322],"iteration":18,"passed_time":0.09459844212,"remaining_time":0.05476751912},
{"learn":[44046.08143],"iteration":19,"passed_time":0.09566710124,"remaining_time":0.04783355062},
{"learn":[43781.65464],"iteration":20,"passed_time":0.09679493211,"remaining_time":0.04148354233},
{"learn":[43509.63411],"iteration":21,"passed_time":0.09793146718,"remaining_time":0.03561144261},
{"learn":[43478.93139],"iteration":22,"passed_time":0.09888698141,"remaining_time":0.03009603782},
{"learn":[43399.03433],"iteration":23,"passed_time":0.09988548751,"remaining_time":0.02497137188},
{"learn":[42951.78103],"iteration":24,"passed_time":0.1056663892,"remaining_time":0.02113327783},
{"learn":[42824.77972],"iteration":25,"passed_time":0.1081888365,"remaining_time":0.01664443638},
{"learn":[42524.58644],"iteration":26,"passed_time":0.1096272279,"remaining_time":0.0121808031},
{"learn":[42425.52417],"iteration":27,"passed_time":0.1119146193,"remaining_time":0.007993901382},
{"learn":[42232.53606],"iteration":28,"passed_time":0.1132849792,"remaining_time":0.003906378595},
{"learn":[41988.3815],"iteration":29,"passed_time":0.11490505,"remaining_time":0}
]}